django_oidc_tf-0.0.8.dist-info/DESCRIPTION.rst
django_oidc_tf-0.0.8.dist-info/METADATA
django_oidc_tf-0.0.8.dist-info/RECORD
django_oidc_tf-0.0.8.dist-info/WHEEL
django_oidc_tf-0.0.8.dist-info/metadata.json
django_oidc_tf-0.0.8.dist-info/top_level.txt
djangooidc/__init__.py
djangooidc/backends.py
djangooidc/exceptions.py
djangooidc/oidc.py
djangooidc/status.py
djangooidc/tests.py
djangooidc/urls.py
djangooidc/views.py
djangooidc/templates/djangooidc/base.html
djangooidc/templates/djangooidc/error.html
djangooidc/templates/djangooidc/login.html
