Metadata-Version: 2.0
Name: django-oidc-tf
Version: 0.0.8
Summary: A Django OpenID Connect (OIDC) authentication backend
Home-page: https://github.com/py-pa/django-oidc
Author: Thomas Frössman
Author-email: thomasf@jossystem.se
License: Apache Software License
Keywords: repo_name
Platform: UNKNOWN
Classifier: Environment :: Web Environment
Classifier: Development Status :: 4 - Beta
Classifier: Framework :: Django
Classifier: Intended Audience :: Developers
Classifier: License :: OSI Approved :: Apache Software License
Classifier: Operating System :: OS Independent
Classifier: Natural Language :: English
Classifier: Programming Language :: Python :: 3.5
Requires-Dist: django (>=1.10)
Requires-Dist: oic (>=0.10.0)
